{"todos":[{"id":1772359035090,"text":"做一个竞彩预测系统","completed":false,"type":"longterm","dueDate":"2026-03-01","completedDate":null,"xpReward":50},{"id":1772352025765,"text":"做一个智能体项目","completed":false,"type":"longterm","dueDate":"2026-03-01","completedDate":null,"xpReward":50},{"id":1772342759540,"text":"mcp，skills底层","completed":false,"type":"longterm","dueDate":"2026-03-01","completedDate":null,"xpReward":50},{"id":1771638875315,"text":"调查人类历史上几次工业革命","completed":false,"type":"longterm","dueDate":"2026-02-21","completedDate":null,"xpReward":50},{"id":1771231265365,"text":"openclaw自动部署项目","completed":false,"type":"daily","dueDate":"2026-02-16","completedDate":null,"xpReward":20},{"id":1771230572340,"text":"做一个关于openclaw切换大模型的项目","completed":false,"type":"daily","dueDate":"2026-02-16","completedDate":null,"xpReward":20},{"id":1770736316806,"text":"加入moltbook","completed":false,"type":"daily","dueDate":"2026-02-10","completedDate":null,"xpReward":20},{"id":1770735515762,"text":"部署openclaw","completed":false,"type":"longterm","dueDate":"2026-02-10","completedDate":null,"xpReward":50},{"id":1770726596475,"text":"端口有什么用","completed":false,"type":"daily","dueDate":"2026-02-10","completedDate":null,"xpReward":20},{"id":1770625268517,"text":"学习使用vercel","completed":true,"type":"daily","dueDate":"2026-02-09","completedDate":"2026-03-02","xpReward":20},{"id":1770609776354,"text":"制作一个获取热点信息的网站","completed":false,"type":"daily","dueDate":"2026-02-09","completedDate":null,"xpReward":20},{"id":1770213765193,"text":"学习编程导航","completed":false,"type":"longterm","dueDate":"2026-02-04","completedDate":null,"xpReward":50},{"id":1770213750927,"text":"关注欧洲加拿大留学学校","completed":false,"type":"longterm","dueDate":"2026-02-04","completedDate":null,"xpReward":50},{"id":1770213590114,"text":"做个人博客","completed":false,"type":"longterm","dueDate":"2026-02-04","completedDate":null,"xpReward":50},{"id":1770133982596,"text":"关注留学","completed":true,"type":"longterm","dueDate":"2026-02-03","completedDate":"2026-02-04","xpReward":50},{"id":1769856602170,"text":"美化to do list","completed":false,"type":"longterm","dueDate":"2026-01-31","completedDate":null,"xpReward":50}],"xp":70,"level":1}